{
  "note": "Top by score via PullPush archive (live Reddit API blocked). Refreshed when worker can pull.",
  "thoughts": [
    {
      "created_utc": 1549676620,
      "score": 188884,
      "id": "aonp75",
      "title": "Whoever created the tradition of not seeing the bride in the wedding dress beforehand saved countless husbands everywhere from hours of dress shopping and will forever be a hero to all men.",
      "url": "https://www.reddit.com/r/Showerthoughts/comments/aonp75/whoever_created_the_tradition_of_not_seeing_the/"
    },
    {
      "created_utc": 1578174650,
      "score": 170542,
      "id": "ek33p5",
      "title": "We laugh at dogs getting excited when they hear a bark on TV, but if TV was a nonstop stream of unintelligible noises and then someone suddenly spoke to you in your language, you'd be pretty fucking startled too.",
      "url": "https://www.reddit.com/r/Showerthoughts/comments/ek33p5/we_laugh_at_dogs_getting_excited_when_they_hear_a/"
    },
    {
      "created_utc": 1551495306,
      "score": 161757,
      "id": "awd10u",
      "title": "When you're a kid, you don't realize you're also watching your mom and dad grow up.",
      "url": "https://www.reddit.com/r/Showerthoughts/comments/awd10u/when_youre_a_kid_you_dont_realize_youre_also/"
    },
    {
      "created_utc": 1562270134,
      "score": 146530,
      "id": "c96xkf",
      "title": "Everyone hates being sung happy birthday, and everyone hates singing happy birthday, so what the fuck are we doing here.",
      "url": "https://www.reddit.com/r/Showerthoughts/comments/c96xkf/everyone_hates_being_sung_happy_birthday_and/"
    },
    {
      "created_utc": 1528142598,
      "score": 143572,
      "id": "8okexh",
      "title": "George Washington died in 1799. The first dinosaur fossil was discovered in 1824. George Washington never knew dinosaurs existed.",
      "url": "https://www.reddit.com/r/Showerthoughts/comments/8okexh/george_washington_died_in_1799_the_first_dinosaur/"
    },
    {
      "created_utc": 1565463191,
      "score": 139105,
      "id": "com04g",
      "title": "Dads probably bond with dogs so much because, in our society, men don’t get shown a lot of affection but dogs give tons of affection regardless",
      "url": "https://www.reddit.com/r/Showerthoughts/comments/com04g/dads_probably_bond_with_dogs_so_much_because_in/"
    },
    {
      "created_utc": 1578875274,
      "score": 137076,
      "id": "enw8rz",
      "title": "If elevators hadn't been invented, all the CEOs and important people would have their offices on the first floor as a sign of status.",
      "url": "https://www.reddit.com/r/Showerthoughts/comments/enw8rz/if_elevators_hadnt_been_invented_all_the_ceos_and/"
    },
    {
      "created_utc": 1574074286,
      "score": 136303,
      "id": "dy1no2",
      "title": "Pavlov probably thought about feeding his dogs every time someone rang a bell.",
      "url": "https://www.reddit.com/r/Showerthoughts/comments/dy1no2/pavlov_probably_thought_about_feeding_his_dogs/"
    },
    {
      "created_utc": 1574545331,
      "score": 135952,
      "id": "e0omqn",
      "title": "During a nuclear explosion, there is a certain distance of the radius where all the frozen supermarket pizzas are cooked to perfection.",
      "url": "https://www.reddit.com/r/Showerthoughts/comments/e0omqn/during_a_nuclear_explosion_there_is_a_certain/"
    },
    {
      "created_utc": 1587322060,
      "score": 135722,
      "id": "g4d0ij",
      "title": "Being able to tolerate the sound of your own voice in a video is probably the highest form of self acceptance.",
      "url": "https://www.reddit.com/r/Showerthoughts/comments/g4d0ij/being_able_to_tolerate_the_sound_of_your_own/"
    }
  ],
  "source": "r/showerthoughts",
  "cached_at": "2026-07-16T22:35:29.7776105Z"
}